wing_carrier-1.1.4.dist-info/licenses/LICENSE
wingcarrier/__init__.py
wingcarrier/wingdbstub.py
wingcarrier/3rdparty/cascadeur/wing_cmds/__init__.py
wingcarrier/3rdparty/cascadeur/wing_cmds/wing_connect.py
wingcarrier/pigeons/__init__.py
wingcarrier/pigeons/cascadeur.py
wingcarrier/pigeons/maya.py
wingcarrier/pigeons/pigeon.py
wingcarrier/pigeons/test_file.py
wingcarrier/winghotkeys/dispatcher.py
wing_carrier-1.1.4.dist-info/METADATA
wing_carrier-1.1.4.dist-info/WHEEL
wing_carrier-1.1.4.dist-info/top_level.txt
wing_carrier-1.1.4.dist-info/RECORD
