Metadata-Version: 2.4
Name: wing-carrier
Version: 1.1.4
Summary: Send commands from Wing-IDE to DCC apps or between DCC apps
Author-email: Nathaniel A <developer@3dcg.guru>
Project-URL: Homepage, https://github.com/Nathanieljla/wing-carrier
Classifier: Programming Language :: Python :: 3
Classifier: Operating System :: OS Independent
Requires-Python: >=3.4
License-File: LICENSE
Dynamic: license-file
